{"is_source_file": true, "format": "CSS", "description": "This file contains CSS code for styling a static website, specifically for theme management and layout of the application. It includes variables for light and dark themes and styles for various components of the application.", "external_files": [], "external_methods": [], "published": [], "classes": [{"name": "App", "description": "Main styling class for the application, setting background color and text color based on the theme."}, {"name": "App-logo", "description": "Styling for the application logo, including size and animation."}, {"name": "App-header", "description": "Header style including background color and layout for aligning items."}, {"name": "App-link", "description": "Styling for links, defining color and transition effects."}, {"name": "theme-toggle", "description": "Button for toggling between light and dark themes, styled with position, colors, and hover effects."}], "methods": [], "calls": [], "search-terms": ["theme management", "light theme", "dark theme", "responsive design"], "state": 2, "file_id": 5, "knowledge_revision": 22, "git_revision": "25aac61aaf5df07b3cd3ebda3f0d5858dd6dff93", "hash": "22f9e17cc1848b56dbb244518ac2707e", "format-version": 4, "code-base-name": "static_website_frontend", "filename": "static_website_frontend/src/App.css", "revision_history": [{"22": "25aac61aaf5df07b3cd3ebda3f0d5858dd6dff93"}]}